rich_dataframe/__init__.py
rich_dataframe/rich_dataframe.py
rich_dataframe2-0.2.1.dist-info/LICENSE
rich_dataframe2-0.2.1.dist-info/METADATA
rich_dataframe2-0.2.1.dist-info/WHEEL
rich_dataframe2-0.2.1.dist-info/RECORD
