Metadata-Version: 2.1
Name: rich-dataframe2
Version: 0.2.1
Summary: Create animated and pretty Pandas Dataframe
Home-page: https://github.com/khuyentran1401/rich-dataframe
License: Apache-2.0
Keywords: pandas
Author: khuyentran1401
Author-email: khuyentran1476@gmail.com
Requires-Python: >=3.9,<4.0
Classifier: License :: OSI Approved :: Apache Software License
Classifier: Programming Language :: Python :: 3
Classifier: Programming Language :: Python :: 3.9
Classifier: Programming Language :: Python :: 3.10
Classifier: Programming Language :: Python :: 3.11
Classifier: Programming Language :: Python :: 3.12
Requires-Dist: pandas (>=2,<3)
Requires-Dist: rich
Requires-Dist: scikit-learn (>=1.3,<2.0)
Project-URL: Repository, https://github.com/khuyentran1401/rich-dataframe
